MANIFEST.in
setup.py
irclog/__init__.py
irclog/archive.py
irclog/messages.py
irclog/parser.py
irclog/tests.py
irclog/version.py
irclog.egg-info/PKG-INFO
irclog.egg-info/SOURCES.txt
irclog.egg-info/dependency_links.txt
irclog.egg-info/requires.txt
irclog.egg-info/top_level.txt
irclog/web/__init__.py
irclog/web/server.py
irclog/web/templates/basic/archive.html
irclog/web/templates/basic/base.html
irclog/web/templates/basic/channel.html
irclog/web/templates/basic/favicon.ico
irclog/web/templates/basic/log.html
irclog/web/templates/basic/server.html
irclog/web/templates/basic/style.css