Metadata-Version: 1.0
Name: irclog
Version: 0.2.0
Summary: The web IRC loger view.
Home-page: http://irclog.rtfd.org/
Author: Hong MinHee
Author-email: minhee@dahlia.kr
License: MIT License
Platform: UNKNOWN
Classifier: Development Status :: 3 - Alpha
Classifier: Intended Audience :: Developers
Classifier: Intended Audience :: End Users/Desktop
Classifier: License :: OSI Approved :: MIT License
Classifier: Topic :: Communications :: Chat :: Internet Relay Chat
Classifier: Topic :: Internet :: WWW/HTTP :: WSGI :: Application
Classifier: Topic :: System :: Logging
